walrus/__init__.py
walrus/autocomplete.py
walrus/cache.py
walrus/containers.py
walrus/counter.py
walrus/database.py
walrus/fts.py
walrus/graph.py
walrus/lock.py
walrus/models.py
walrus/query.py
walrus/rate_limit.py
walrus/stopwords.txt
walrus/streams.py
walrus/utils.py
walrus/scripts/__init__.py
walrus/scripts/array_append.lua
walrus/scripts/array_extend.lua
walrus/scripts/array_get.lua
walrus/scripts/array_pop.lua
walrus/scripts/array_remove.lua
walrus/scripts/array_set.lua
walrus/scripts/cas.lua
walrus/scripts/lock_acquire.lua
walrus/scripts/lock_release.lua
walrus/scripts/rate_limit.lua
walrus/scripts/zset_score_filter.lua
walrus/search/__init__.py
walrus/search/metaphone.py
walrus/search/porter.py
walrus/tests/__init__.py
walrus/tests/autocomplete.py
walrus/tests/base.py
walrus/tests/cache.py
walrus/tests/containers.py
walrus/tests/counter.py
walrus/tests/database.py
walrus/tests/fts.py
walrus/tests/graph.py
walrus/tests/lock.py
walrus/tests/models.py
walrus/tests/rate_limit.py
walrus/tests/streams.py
walrus/tusks/__init__.py
walrus/tusks/helpers.py
walrus/tusks/ledisdb.py
walrus/tusks/rlite.py
walrus/tusks/vedisdb.py
walrus-0.9.7.dist-info/licenses/LICENSE
walrus-0.9.7.dist-info/METADATA
walrus-0.9.7.dist-info/WHEEL
walrus-0.9.7.dist-info/top_level.txt
walrus-0.9.7.dist-info/RECORD
