Metadata-Version: 2.4
Name: walrus
Version: 0.9.7
Summary: a set of utilities for working with redis
Author-email: Charles Leifer <coleifer@gmail.com>
Project-URL: Repository, https://github.com/coleifer/walrus
Project-URL: Documentation, https://walrus.readthedocs.io/
Project-URL: Changelog, https://github.com/coleifer/walrus/blob/master/CHANGELOG.md
Classifier: Programming Language :: Python :: 2
Classifier: Programming Language :: Python :: 3
Classifier: Topic :: Software Development :: Libraries :: Python Modules
License-File: LICENSE
Requires-Dist: redis
Dynamic: license-file
